pifpaf/__init__.py
pifpaf/__main__.py
pifpaf/util.py
pifpaf/drivers/__init__.py
pifpaf/drivers/aodh.py
pifpaf/drivers/artemis.py
pifpaf/drivers/ceph.py
pifpaf/drivers/consul.py
pifpaf/drivers/couchdb.py
pifpaf/drivers/elasticsearch.py
pifpaf/drivers/etcd.py
pifpaf/drivers/fakes3.py
pifpaf/drivers/gnocchi.py
pifpaf/drivers/httpbin.py
pifpaf/drivers/influxdb.py
pifpaf/drivers/kafka.py
pifpaf/drivers/keystone.py
pifpaf/drivers/memcached.py
pifpaf/drivers/mongodb.py
pifpaf/drivers/mysql.py
pifpaf/drivers/postgresql.py
pifpaf/drivers/qdrouterd.py
pifpaf/drivers/rabbitmq.py
pifpaf/drivers/redis.py
pifpaf/drivers/s3rver.py
pifpaf/drivers/swift.py
pifpaf/drivers/valkey.py
pifpaf/drivers/vault.py
pifpaf/drivers/zookeeper.py
pifpaf/drivers/templates/artemis/broker.xml
pifpaf/drivers/templates/qdrouterd/broker_om.conf.inc
pifpaf/drivers/templates/qdrouterd/direct_om.conf.inc
pifpaf/drivers/templates/qdrouterd/qdrouterd.conf
pifpaf/drivers/templates/qdrouterd/sasl_qdrouterd.conf
pifpaf/drivers/templates/swift/account.conf
pifpaf/drivers/templates/swift/common.conf.inc
pifpaf/drivers/templates/swift/container-sync-realms.conf
pifpaf/drivers/templates/swift/container.conf
pifpaf/drivers/templates/swift/object.conf
pifpaf/drivers/templates/swift/proxy.conf
pifpaf/drivers/templates/swift/sitecustomize.py
pifpaf/drivers/templates/swift/swift.conf
pifpaf/tests/__init__.py
pifpaf/tests/test_cli.py
pifpaf/tests/test_drivers.py
pifpaf/tests/unkillable.py
pifpaf-3.4.0.dist-info/licenses/LICENSE
pifpaf-3.4.0.dist-info/METADATA
pifpaf-3.4.0.dist-info/WHEEL
pifpaf-3.4.0.dist-info/entry_points.txt
pifpaf-3.4.0.dist-info/top_level.txt
pifpaf-3.4.0.dist-info/RECORD
